hivemind_worker/__init__.py
hivemind_worker/nodepool_pb2.py
hivemind_worker/nodepool_pb2_grpc.py
hivemind_worker/wg0.conf
hivemind_worker/worker_node.py
hivemind_worker/static/css/style.css
hivemind_worker/static/js/monitor.js
hivemind_worker/templates/login.html
hivemind_worker/templates/monitor.html
hivemind_worker-0.0.5.dist-info/METADATA
hivemind_worker-0.0.5.dist-info/WHEEL
hivemind_worker-0.0.5.dist-info/licenses/LICENSE
hivemind_worker-0.0.5.dist-info/RECORD
