Metadata-Version: 2.4
Name: hivemind_worker
Version: 0.0.5
Summary: A hivemind worker_node
Project-URL: Homepage, https://github.com/him6794/hivemind
Project-URL: Bug Tracker, https://github.com/him6794/hivemind/issues
Author-email: Example Author <hivemind@justin0711.com>
License-File: LICENSE
Classifier: License :: OSI Approved :: MIT License
Classifier: Operating System :: OS Independent
Classifier: Programming Language :: Python :: 3
Requires-Python: >=3.7
Requires-Dist: docker>=7.0.0
Requires-Dist: flask>=2.3.0
Requires-Dist: grpcio-tools>=1.62.0
Requires-Dist: grpcio>=1.62.0
Requires-Dist: netifaces>=0.11.0
Requires-Dist: protobuf>=4.0.0
Requires-Dist: psutil>=5.9.0
Requires-Dist: requests>=2.32.0
